odoo_index_mcp/__init__.py
odoo_index_mcp/config.py
odoo_index_mcp/database.py
odoo_index_mcp/dependency_tree.py
odoo_index_mcp/indexer.py
odoo_index_mcp/server.py
odoo_index_mcp/tools.py
odoo_index_mcp/parsers/__init__.py
odoo_index_mcp/parsers/csv_parser.py
odoo_index_mcp/parsers/manifest_parser.py
odoo_index_mcp/parsers/python_parser.py
odoo_index_mcp/parsers/xml_parser.py
odoo_index_mcp-0.1.0.dist-info/METADATA
odoo_index_mcp-0.1.0.dist-info/WHEEL
odoo_index_mcp-0.1.0.dist-info/entry_points.txt
odoo_index_mcp-0.1.0.dist-info/licenses/LICENSE
odoo_index_mcp-0.1.0.dist-info/RECORD
