Metadata-Version: 2.4
Name: odoo-index-mcp
Version: 0.1.0
Summary: Lightweight MCP server for indexing Odoo code
Project-URL: Homepage, https://github.com/letzdoo/odoo-indexer-mcp
Project-URL: Repository, https://github.com/letzdoo/odoo-indexer-mcp
Project-URL: Issues, https://github.com/letzdoo/odoo-indexer-mcp/issues
Author-email: "Letzdoo (Jerome Sonnet)" <jerome.sonnet@letzdoo.com>
License: MIT
License-File: LICENSE
Keywords: code-search,indexer,mcp,model-context-protocol,odoo
Classifier: Development Status :: 4 - Beta
Classifier: Intended Audience :: Developers
Classifier: License :: OSI Approved :: MIT License
Classifier: Programming Language :: Python :: 3
Classifier: Programming Language :: Python :: 3.10
Classifier: Programming Language :: Python :: 3.11
Classifier: Programming Language :: Python :: 3.12
Classifier: Topic :: Software Development :: Code Generators
Classifier: Topic :: Software Development :: Libraries :: Python Modules
Requires-Python: >=3.10
Requires-Dist: aiosqlite>=0.19.0
Requires-Dist: fastmcp>=2.5.0
Requires-Dist: lxml>=4.9.0
Requires-Dist: python-dotenv>=1.0.0
Requires-Dist: uvloop>=0.21.0
